publixPassportAPI/__init__.py
publixPassportAPI/publix.py
publixpassportapi-0.0.3.dist-info/METADATA
publixpassportapi-0.0.3.dist-info/WHEEL
publixpassportapi-0.0.3.dist-info/licenses/LICENSE
publixpassportapi-0.0.3.dist-info/RECORD
