Metadata-Version: 2.3
Name: publixPassportAPI
Version: 0.0.3
Summary: A python API to interact with Publix Passport API. Get your schedule, and recent pay statement history.   https://github.com/AidanB446/publixPassportAPI
Project-URL: Homepage, https://github.com/AidanB446/publixPassportAPI
Project-URL: Issues, https://github.com/AidanB446/publixPassportAPI/issues
Author-email: Aidan Bruner <aidanbruner789@gmail.com>
License-File: LICENSE
Classifier: License :: OSI Approved :: MIT License
Classifier: Operating System :: OS Independent
Classifier: Programming Language :: Python :: 3
Requires-Python: >=3.10
Requires-Dist: selenium==4.21.0
